luffybot/__init__.py
luffybot/__main__.py
luffybot/categinex.py
luffybot/interwikiwp.py
luffybot/ping.py
luffybot/stopifpdd.py
luffybot/ébauche.py
luffybot-1.0.0.dist-info/METADATA
luffybot-1.0.0.dist-info/WHEEL
luffybot-1.0.0.dist-info/entry_points.txt
luffybot-1.0.0.dist-info/top_level.txt
luffybot-1.0.0.dist-info/RECORD
