Metadata-Version: 2.4
Name: luffybot
Version: 1.0.0
Summary: Un bot Pywikibot pour Vikidia effectuant des tâches de maintenance répétitives
Author-email: LuffyDev <luffy@leblogcubing.fr>
License-Expression: MIT
Requires-Python: >=3.7
Requires-Dist: pywikibot
